metadata_driver_azure/__init__.py
metadata_driver_azure/computing_plugin.py
metadata_driver_azure/config.py
metadata_driver_azure/data_plugin.py
metadata_driver_azure/log.py
metadata_driver_azure/utils.py
nevermined_metadata_driver_azure-0.1.0.dist-info/LICENSE
nevermined_metadata_driver_azure-0.1.0.dist-info/METADATA
nevermined_metadata_driver_azure-0.1.0.dist-info/NOTICE
nevermined_metadata_driver_azure-0.1.0.dist-info/WHEEL
nevermined_metadata_driver_azure-0.1.0.dist-info/top_level.txt
nevermined_metadata_driver_azure-0.1.0.dist-info/RECORD
